{
  "schemaVersion": "1.0",
  "revisionSlug": "revisao-demo-pipeline",
  "title": "Revisão Demo — Proporcionalidade e Regra de Três",
  "grade": "7º ano",
  "subject": "Matemática",
  "description": "Revisão sintética autoral para validar o pipeline externo de PDFs. Cobre proporção direta, proporção inversa e regra de três simples.",
  "visualConfig": {
    "subtitle": "Revisão sintética autoral para validar o pipeline externo de",
    "subject": "Matemática",
    "tone": "performance",
    "missionMapBadge": "2 missões"
  },
  "missions": [
    {
      "slug": "proporcao-direta",
      "title": "Proporção Direta — Quando mais é mais",
      "shortTitle": "Proporção Direta",
      "goal": "O aluno será capaz de identificar grandezas diretamente proporcionais e resolver problemas usando regra de três direta.",
      "estimatedMinutes": 8,
      "isOptional": false,
      "prerequisites": [],
      "blocks": [
        {
          "type": "intro",
          "title": "Proporção Direta — Quando mais é mais",
          "text": "O aluno será capaz de identificar grandezas diretamente proporcionais e resolver problemas usando regra de três direta."
        },
        {
          "type": "concept",
          "title": "Conceito central",
          "text": "Duas grandezas são diretamente proporcionais quando, ao aumentar uma, a outra aumenta na mesma razão. Exemplo: distância e tempo (a velocidade constante). Se o tempo dobra, a distância dobra. A razão entre os valores correspondentes é sempre a mesma: A₁/B₁ = A₂/B₂.",
          "highlight": "Duas grandezas são diretamente proporcionais quando, ao aumentar uma, a outra aumenta na mesma razão."
        },
        {
          "type": "worked_example",
          "problem": "Um carro percorre 120 km em 2 horas. Quantos km percorre em 5 horas à mesma velocidade?",
          "steps": [
            "Identifique: distância e tempo são diretamente proporcionais (velocidade constante).",
            "Monte a proporção: 120/2 = x/5.",
            "Resolva: x = 120 × 5 / 2 = 300 km."
          ],
          "conclusion": "Em 5 horas, o carro percorre 300 km."
        },
        {
          "type": "summary",
          "title": "Resumo",
          "points": [
            "Duas grandezas são diretamente proporcionais quando, ao aumentar uma, a outra aumenta na mesma razão.",
            "Exemplo: distância e tempo (a velocidade constante). Se o tempo dobra, a distância dobra.",
            "A razão entre os valores correspondentes é sempre a mesma: A₁/B₁ = A₂/B₂."
          ]
        }
      ],
      "questions": [
        {
          "type": "multiple_choice",
          "difficulty": "basic",
          "skillTag": "identificar-proporcionalidade",
          "statement": "[PLACEHOLDER 1] Questão sobre \"Proporção Direta — Quando mais é mais\" — habilidade: identificar-proporcionalidade. REESCREVA esta questão antes de importar.",
          "options": [
            {
              "text": "Alternativa correta (reescreva)",
              "isCorrect": true,
              "feedback": "Correto. Explique aqui por que esta resposta está certa.",
              "errorCategory": null
            },
            {
              "text": "Alternativa incorreta A (reescreva)",
              "isCorrect": false,
              "feedback": "Não. conceito base — explique o erro típico aqui.",
              "errorCategory": "conceito base"
            },
            {
              "text": "Alternativa incorreta B (reescreva)",
              "isCorrect": false,
              "feedback": "Não. Explique o raciocínio correto aqui.",
              "errorCategory": "interpretação"
            }
          ]
        },
        {
          "type": "multiple_choice",
          "difficulty": "intermediate",
          "skillTag": "montar-regra-de-tres",
          "statement": "[PLACEHOLDER 2] Questão sobre \"Proporção Direta — Quando mais é mais\" — habilidade: montar-regra-de-tres. REESCREVA esta questão antes de importar.",
          "options": [
            {
              "text": "Alternativa correta (reescreva)",
              "isCorrect": true,
              "feedback": "Correto. Explique aqui por que esta resposta está certa.",
              "errorCategory": null
            },
            {
              "text": "Alternativa incorreta A (reescreva)",
              "isCorrect": false,
              "feedback": "Não. conceito base — explique o erro típico aqui.",
              "errorCategory": "conceito base"
            },
            {
              "text": "Alternativa incorreta B (reescreva)",
              "isCorrect": false,
              "feedback": "Não. Explique o raciocínio correto aqui.",
              "errorCategory": "interpretação"
            }
          ]
        },
        {
          "type": "multiple_choice",
          "difficulty": "challenge",
          "skillTag": "calcular-valor-desconhecido",
          "statement": "[PLACEHOLDER 3] Questão sobre \"Proporção Direta — Quando mais é mais\" — habilidade: calcular-valor-desconhecido. REESCREVA esta questão antes de importar.",
          "options": [
            {
              "text": "Alternativa correta (reescreva)",
              "isCorrect": true,
              "feedback": "Correto. Explique aqui por que esta resposta está certa.",
              "errorCategory": null
            },
            {
              "text": "Alternativa incorreta A (reescreva)",
              "isCorrect": false,
              "feedback": "Não. conceito base — explique o erro típico aqui.",
              "errorCategory": "conceito base"
            },
            {
              "text": "Alternativa incorreta B (reescreva)",
              "isCorrect": false,
              "feedback": "Não. Explique o raciocínio correto aqui.",
              "errorCategory": "interpretação"
            }
          ]
        },
        {
          "type": "multiple_choice",
          "difficulty": "basic",
          "skillTag": "identificar-proporcionalidade",
          "statement": "[PLACEHOLDER 4] Questão sobre \"Proporção Direta — Quando mais é mais\" — habilidade: identificar-proporcionalidade. REESCREVA esta questão antes de importar.",
          "options": [
            {
              "text": "Alternativa correta (reescreva)",
              "isCorrect": true,
              "feedback": "Correto. Explique aqui por que esta resposta está certa.",
              "errorCategory": null
            },
            {
              "text": "Alternativa incorreta A (reescreva)",
              "isCorrect": false,
              "feedback": "Não. conceito base — explique o erro típico aqui.",
              "errorCategory": "conceito base"
            },
            {
              "text": "Alternativa incorreta B (reescreva)",
              "isCorrect": false,
              "feedback": "Não. Explique o raciocínio correto aqui.",
              "errorCategory": "interpretação"
            }
          ]
        },
        {
          "type": "multiple_choice",
          "difficulty": "intermediate",
          "skillTag": "montar-regra-de-tres",
          "statement": "[PLACEHOLDER 5] Questão sobre \"Proporção Direta — Quando mais é mais\" — habilidade: montar-regra-de-tres. REESCREVA esta questão antes de importar.",
          "options": [
            {
              "text": "Alternativa correta (reescreva)",
              "isCorrect": true,
              "feedback": "Correto. Explique aqui por que esta resposta está certa.",
              "errorCategory": null
            },
            {
              "text": "Alternativa incorreta A (reescreva)",
              "isCorrect": false,
              "feedback": "Não. conceito base — explique o erro típico aqui.",
              "errorCategory": "conceito base"
            },
            {
              "text": "Alternativa incorreta B (reescreva)",
              "isCorrect": false,
              "feedback": "Não. Explique o raciocínio correto aqui.",
              "errorCategory": "interpretação"
            }
          ]
        }
      ]
    },
    {
      "slug": "proporcao-inversa",
      "title": "Proporção Inversa — Quando mais é menos",
      "shortTitle": "Proporção Inversa",
      "goal": "O aluno será capaz de identificar grandezas inversamente proporcionais e resolver problemas usando regra de três inversa.",
      "estimatedMinutes": 8,
      "isOptional": false,
      "prerequisites": [
        "proporcao-direta"
      ],
      "blocks": [
        {
          "type": "intro",
          "title": "Proporção Inversa — Quando mais é menos",
          "text": "O aluno será capaz de identificar grandezas inversamente proporcionais e resolver problemas usando regra de três inversa."
        },
        {
          "type": "concept",
          "title": "Conceito central",
          "text": "Duas grandezas são inversamente proporcionais quando, ao aumentar uma, a outra diminui na mesma razão. Exemplo: número de trabalhadores e tempo para concluir uma tarefa. Mais trabalhadores → menos tempo. Na regra de três inversa, inverte-se um dos membros antes de resolver: A₁/A₂ = B₂/B₁.",
          "highlight": "Duas grandezas são inversamente proporcionais quando, ao aumentar uma, a outra diminui na mesma razão."
        },
        {
          "type": "worked_example",
          "problem": "3 pintores pintam uma casa em 12 dias. Em quantos dias 4 pintores pintariam a mesma casa?",
          "steps": [
            "Identifique: pintores e dias são inversamente proporcionais (mais pintores → menos dias).",
            "Monte a proporção inversa: 3/4 = x/12 — inverta um dos membros: 3 × 12 = 4 × x.",
            "Resolva: x = 36 / 4 = 9 dias."
          ],
          "conclusion": "4 pintores pintam a casa em 9 dias."
        },
        {
          "type": "summary",
          "title": "Resumo",
          "points": [
            "Duas grandezas são inversamente proporcionais quando, ao aumentar uma, a outra diminui na mesma razão.",
            "Exemplo: número de trabalhadores e tempo para concluir uma tarefa. Mais trabalhadores → menos tempo.",
            "Na regra de três inversa, inverte-se um dos membros antes de resolver: A₁/A₂ = B₂/B₁."
          ]
        }
      ],
      "questions": [
        {
          "type": "multiple_choice",
          "difficulty": "basic",
          "skillTag": "identificar-proporcionalidade-inversa",
          "statement": "[PLACEHOLDER 1] Questão sobre \"Proporção Inversa — Quando mais é menos\" — habilidade: identificar-proporcionalidade-inversa. REESCREVA esta questão antes de importar.",
          "options": [
            {
              "text": "Alternativa correta (reescreva)",
              "isCorrect": true,
              "feedback": "Correto. Explique aqui por que esta resposta está certa.",
              "errorCategory": null
            },
            {
              "text": "Alternativa incorreta A (reescreva)",
              "isCorrect": false,
              "feedback": "Não. conceito base — explique o erro típico aqui.",
              "errorCategory": "conceito base"
            },
            {
              "text": "Alternativa incorreta B (reescreva)",
              "isCorrect": false,
              "feedback": "Não. Explique o raciocínio correto aqui.",
              "errorCategory": "interpretação"
            }
          ]
        },
        {
          "type": "multiple_choice",
          "difficulty": "intermediate",
          "skillTag": "inverter-membros-proporcao",
          "statement": "[PLACEHOLDER 2] Questão sobre \"Proporção Inversa — Quando mais é menos\" — habilidade: inverter-membros-proporcao. REESCREVA esta questão antes de importar.",
          "options": [
            {
              "text": "Alternativa correta (reescreva)",
              "isCorrect": true,
              "feedback": "Correto. Explique aqui por que esta resposta está certa.",
              "errorCategory": null
            },
            {
              "text": "Alternativa incorreta A (reescreva)",
              "isCorrect": false,
              "feedback": "Não. conceito base — explique o erro típico aqui.",
              "errorCategory": "conceito base"
            },
            {
              "text": "Alternativa incorreta B (reescreva)",
              "isCorrect": false,
              "feedback": "Não. Explique o raciocínio correto aqui.",
              "errorCategory": "interpretação"
            }
          ]
        },
        {
          "type": "multiple_choice",
          "difficulty": "challenge",
          "skillTag": "resolver-regra-de-tres-inversa",
          "statement": "[PLACEHOLDER 3] Questão sobre \"Proporção Inversa — Quando mais é menos\" — habilidade: resolver-regra-de-tres-inversa. REESCREVA esta questão antes de importar.",
          "options": [
            {
              "text": "Alternativa correta (reescreva)",
              "isCorrect": true,
              "feedback": "Correto. Explique aqui por que esta resposta está certa.",
              "errorCategory": null
            },
            {
              "text": "Alternativa incorreta A (reescreva)",
              "isCorrect": false,
              "feedback": "Não. conceito base — explique o erro típico aqui.",
              "errorCategory": "conceito base"
            },
            {
              "text": "Alternativa incorreta B (reescreva)",
              "isCorrect": false,
              "feedback": "Não. Explique o raciocínio correto aqui.",
              "errorCategory": "interpretação"
            }
          ]
        },
        {
          "type": "multiple_choice",
          "difficulty": "basic",
          "skillTag": "identificar-proporcionalidade-inversa",
          "statement": "[PLACEHOLDER 4] Questão sobre \"Proporção Inversa — Quando mais é menos\" — habilidade: identificar-proporcionalidade-inversa. REESCREVA esta questão antes de importar.",
          "options": [
            {
              "text": "Alternativa correta (reescreva)",
              "isCorrect": true,
              "feedback": "Correto. Explique aqui por que esta resposta está certa.",
              "errorCategory": null
            },
            {
              "text": "Alternativa incorreta A (reescreva)",
              "isCorrect": false,
              "feedback": "Não. conceito base — explique o erro típico aqui.",
              "errorCategory": "conceito base"
            },
            {
              "text": "Alternativa incorreta B (reescreva)",
              "isCorrect": false,
              "feedback": "Não. Explique o raciocínio correto aqui.",
              "errorCategory": "interpretação"
            }
          ]
        },
        {
          "type": "multiple_choice",
          "difficulty": "intermediate",
          "skillTag": "inverter-membros-proporcao",
          "statement": "[PLACEHOLDER 5] Questão sobre \"Proporção Inversa — Quando mais é menos\" — habilidade: inverter-membros-proporcao. REESCREVA esta questão antes de importar.",
          "options": [
            {
              "text": "Alternativa correta (reescreva)",
              "isCorrect": true,
              "feedback": "Correto. Explique aqui por que esta resposta está certa.",
              "errorCategory": null
            },
            {
              "text": "Alternativa incorreta A (reescreva)",
              "isCorrect": false,
              "feedback": "Não. conceito base — explique o erro típico aqui.",
              "errorCategory": "conceito base"
            },
            {
              "text": "Alternativa incorreta B (reescreva)",
              "isCorrect": false,
              "feedback": "Não. Explique o raciocínio correto aqui.",
              "errorCategory": "interpretação"
            }
          ]
        }
      ]
    }
  ]
}